<?xml version="1.0" encoding="utf-8"?>
<!-- *
 * This software is distributed in the hope that it will be useful,
 * but is distributed on an "AS IS" BASIS, WITHOUT WARRANTIES OR
 * CONDITIONS OF ANY KIND, without even the implied warranty of
 * MERCHANTABILITY or FITNESS FOR A PARTICULAR PURPOSE.
 *
 * This software may only be used to program products purchased from
 * Analog Devices for incorporation by you into audio products that
 * are intended for resale to audio product end users. This software
 * may not be distributed whole or in any part to third parties.
 *
 * Copyright © 2022 Analog Devices, Inc. All rights reserved.
 */
-->
<!--NetList XML file-->
<NetList>
    <IC name=" IC 1 " type="ADAU1452">
        <Schematic>
            <Algorithm name="SquareWithPhaseAmpAlgS3001" friendlyname="Square Oscillator " cell="VibinDspCoolness.Square1 " location="{X=285, Y=750} " Growth="2 " GrowthB="0 " FS="48000">
                <Link pin="O_C490_A0_P1_out" dir="out" link="Link7" />
            </Algorithm>
            <Algorithm name="SinePhaseGainAlgS3002" friendlyname="Sin Tone with Initial Phase " cell="VibinDspCoolness.Tone1 " location="{X=290, Y=621} " Growth="2 " GrowthB="0 " FS="48000">
                <Link pin="O_C164_A0_P1_out" dir="out" link="Link9" />
            </Algorithm>
            <Algorithm name="SquareWithPhaseAmpAlgS3002" friendlyname="Square Oscillator " cell="VibinDspCoolness.Square1_2 " location="{X=303, Y=1359} " Growth="2 " GrowthB="0 " FS="48000">
                <Link pin="O_C279_A0_P1_out" dir="out" link="Link20" />
            </Algorithm>
            <Algorithm name="SinePhaseGainAlgS3001" friendlyname="Sin Tone with Initial Phase " cell="VibinDspCoolness.Tone1_2 " location="{X=308, Y=1230} " Growth="2 " GrowthB="0 " FS="48000">
                <Link pin="O_C295_A0_P1_out" dir="out" link="Link16" />
            </Algorithm>
            <Algorithm name="AsrcInSigma300Alg2" friendlyname="From ASRC " cell="AsrcIn2 " location="{X=166, Y=577} " Growth="16 " GrowthB="0 " FS="48000">
                <Link pin="O_C25_A0_P1_out" dir="out" link="Link40" />
                <Link pin="O_C25_A0_P2_out" dir="out" link="Link42" />
            </Algorithm>
            <Algorithm name="LinearSweepExTrigAlgBurstS3001" friendlyname="Linear Sweep w/ tone burst " cell="VibinDspCoolness.Sweep1 " location="{X=405, Y=724} " Growth="0 " GrowthB="0">
                <Link pin="I_C455_A0_P1_in" dir="in" link="Link7" />
                <Link pin="O_C455_A0_P2_out" dir="out" link="Link8" />
            </Algorithm>
            <Algorithm name="LinearSweepExTrigAlgBurstS3002" friendlyname="Linear Sweep w/ tone burst " cell="VibinDspCoolness.Sweep1_2 " location="{X=423, Y=1333} " Growth="0 " GrowthB="0">
                <Link pin="I_C274_A0_P1_in" dir="in" link="Link20" />
                <Link pin="O_C274_A0_P2_out" dir="out" link="Link13" />
            </Algorithm>
            <Algorithm name="monoMuxS300Slew1" friendlyname="Mono SW Slew " cell="VibinDspCoolness.Nx1-1 " location="{X=431, Y=643} " Growth="2 " GrowthB="0">
                <Link pin="I_C151_A0_P2_in" dir="in" link="Link9" />
                <Link pin="I_C151_A0_P3_in" dir="in" link="Link8" />
                <Link pin="O_C151_A0_P1_out" dir="out" link="Link10" />
            </Algorithm>
            <Algorithm name="monoMuxS300Slew2" friendlyname="Mono SW Slew " cell="VibinDspCoolness.Nx1-1_2 " location="{X=449, Y=1252} " Growth="2 " GrowthB="0">
                <Link pin="I_C289_A0_P2_in" dir="in" link="Link16" />
                <Link pin="I_C289_A0_P3_in" dir="in" link="Link13" />
                <Link pin="O_C289_A0_P1_out" dir="out" link="Link14" />
            </Algorithm>
            <Algorithm name="NthOrderDoubleS3006" friendlyname="N Channel - Double Precision " cell="VibinDspCoolness.NFilter2 " location="{X=484, Y=325} " Growth="1 " GrowthB="0">
                <Link pin="I_C168_A0_P1_in" dir="in" link="Link40" />
                <Link pin="O_C168_A0_P2_out" dir="out" link="Link0" />
            </Algorithm>
            <Algorithm name="NthOrderDoubleS3004" friendlyname="N Channel - Double Precision " cell="VibinDspCoolness.NFilter1_4 " location="{X=284, Y=487} " Growth="1 " GrowthB="0">
                <Link pin="I_C132_A0_P1_in" dir="in" link="Link40" />
                <Link pin="O_C132_A0_P2_out" dir="out" link="Link4" />
            </Algorithm>
            <Algorithm name="NthOrderDoubleS3008" friendlyname="N Channel - Double Precision " cell="VibinDspCoolness.NFilter2_2 " location="{X=502, Y=934} " Growth="1 " GrowthB="0">
                <Link pin="I_C298_A0_P1_in" dir="in" link="Link42" />
                <Link pin="O_C298_A0_P2_out" dir="out" link="Link19" />
            </Algorithm>
            <Algorithm name="NthOrderDoubleS3007" friendlyname="N Channel - Double Precision " cell="VibinDspCoolness.NFilter1_6 " location="{X=302, Y=1096} " Growth="1 " GrowthB="0">
                <Link pin="I_C249_A0_P1_in" dir="in" link="Link42" />
                <Link pin="O_C249_A0_P2_out" dir="out" link="Link25" />
            </Algorithm>
            <Algorithm name="DelaySigma300Alg2" friendlyname="Growable Delay " cell="Delay_D " location="{X=630, Y=362} " Growth="1 " GrowthB="0">
                <Link pin="I_C108_A0_P1_in" dir="in" link="Link40" />
                <Link pin="O_C108_A0_P2_out" dir="out" link="Link30" />
            </Algorithm>
            <Algorithm name="DelaySigma300PMAlg1" friendlyname="Growable Delay " cell="Delay_D " location="{X=630, Y=362} " Growth="1 " GrowthB="0">
                <Link pin="I_C108_A1_P1_in" dir="in" link="Link42" />
                <Link pin="O_C108_A1_P2_out" dir="out" link="Link32" />
            </Algorithm>
            <Algorithm name="GainAlgNS145X1" friendlyname="Gain (no-slew) " cell="VibinDspCoolness.Gain1 " location="{X=666, Y=348} " Growth="1 " GrowthB="0">
                <Link pin="I_C208_A0_P1_in" dir="in" link="Link0" />
                <Link pin="O_C208_A0_P2_out" dir="out" link="Link1" />
            </Algorithm>
            <Algorithm name="MonoEnvelopeDetectAlgS3001" friendlyname="MS Envelope " cell="VibinDspCoolness.MSEnv1 " location="{X=436, Y=478} " Growth="0 " GrowthB="0">
                <Link pin="I_C391_A0_P1_in" dir="in" link="Link4" />
                <Link pin="O_C391_A0_P2_out" dir="out" link="Link5" />
            </Algorithm>
            <Algorithm name="GainAlgNS145X4" friendlyname="Gain (no-slew) " cell="VibinDspCoolness.Gain1_4 " location="{X=684, Y=957} " Growth="1 " GrowthB="0">
                <Link pin="I_C302_A0_P1_in" dir="in" link="Link19" />
                <Link pin="O_C302_A0_P2_out" dir="out" link="Link22" />
            </Algorithm>
            <Algorithm name="MonoEnvelopeDetectAlgS3002" friendlyname="MS Envelope " cell="VibinDspCoolness.MSEnv1_2 " location="{X=454, Y=1087} " Growth="0 " GrowthB="0">
                <Link pin="I_C270_A0_P1_in" dir="in" link="Link25" />
                <Link pin="O_C270_A0_P2_out" dir="out" link="Link15" />
            </Algorithm>
            <Algorithm name="DCBlockAlgDblPrecS3001" friendlyname="DC Blocking " cell="DCB1 " location="{X=1040, Y=586.4836} " Growth="0 " GrowthB="0">
                <Link pin="I_C29_A0_P1_in" dir="in" link="Link30" />
                <Link pin="O_C29_A0_P2_out" dir="out" link="Link38" />
            </Algorithm>
            <Algorithm name="DCBlockAlgDblPrecS3002" friendlyname="DC Blocking " cell="DCB1 " location="{X=1040, Y=586.4836} " Growth="0 " GrowthB="0">
                <Link pin="I_C29_A1_P1_in" dir="in" link="Link32" />
                <Link pin="O_C29_A1_P2_out" dir="out" link="Link39" />
            </Algorithm>
            <Algorithm name="ExternalGainAlgSlew145X2" friendlyname="Gain (HW slew) " cell="VibinDspCoolness.Slew vol 1 " location="{X=493, Y=640} " Growth="1 " GrowthB="0">
                <Link pin="I_C378_A0_P1_in" dir="in" link="Link5" />
                <Link pin="I_C378_A0_P2_in" dir="in" link="Link10" />
                <Link pin="O_C378_A0_P3_out" dir="out" link="Link6" />
            </Algorithm>
            <Algorithm name="ExternalGainAlgSlew145X3" friendlyname="Gain (HW slew) " cell="VibinDspCoolness.Slew vol 1_2 " location="{X=511, Y=1249} " Growth="1 " GrowthB="0">
                <Link pin="I_C263_A0_P1_in" dir="in" link="Link15" />
                <Link pin="I_C263_A0_P2_in" dir="in" link="Link14" />
                <Link pin="O_C263_A0_P3_out" dir="out" link="Link21" />
            </Algorithm>
            <Algorithm name="OneChanAccuratePeakNoPostGainS300_FullRange2" friendlyname="1-Channel Peak Compressor (Accurate) " cell="VibinDspCoolness.Compressor1_2 " location="{X=843, Y=349} " Growth="0 " GrowthB="0">
                <Link pin="I_C240_A0_P1_in" dir="in" link="Link1" />
                <Link pin="O_C240_A0_P2_out" dir="out" link="Link12" />
            </Algorithm>
            <Algorithm name="OneChanAccuratePeakNoPostGainS300_FullRange4" friendlyname="1-Channel Peak Compressor (Accurate) " cell="VibinDspCoolness.Compressor1_4 " location="{X=861, Y=958} " Growth="0 " GrowthB="0">
                <Link pin="I_C260_A0_P1_in" dir="in" link="Link22" />
                <Link pin="O_C260_A0_P2_out" dir="out" link="Link18" />
            </Algorithm>
            <Algorithm name="ICOutADAU145X1" friendlyname="Output " cell="Output1 " location="{X=1352, Y=419} " Growth="1 " GrowthB="0">
                <Link pin="I_C316_A0_P1_in" dir="in" link="Link38" />
            </Algorithm>
            <Algorithm name="ICOutADAU145X2" friendlyname="Output " cell="Output2 " location="{X=1344, Y=521} " Growth="1 " GrowthB="0">
                <Link pin="I_C318_A0_P1_in" dir="in" link="Link39" />
            </Algorithm>
            <Algorithm name="NthOrderDoubleS3002" friendlyname="N Channel - Double Precision " cell="VibinDspCoolness.NFilter1_2 " location="{X=554, Y=473} " Growth="1 " GrowthB="0">
                <Link pin="I_C45_A0_P1_in" dir="in" link="Link6" />
                <Link pin="O_C45_A0_P2_out" dir="out" link="Link2" />
            </Algorithm>
            <Algorithm name="NthOrderDoubleS3003" friendlyname="N Channel - Double Precision " cell="VibinDspCoolness.NFilter1_3 " location="{X=572, Y=1082} " Growth="1 " GrowthB="0">
                <Link pin="I_C232_A0_P1_in" dir="in" link="Link21" />
                <Link pin="O_C232_A0_P2_out" dir="out" link="Link23" />
            </Algorithm>
            <Algorithm name="GainAlgNS145X2" friendlyname="Gain (no-slew) " cell="VibinDspCoolness.Gain1_2 " location="{X=721, Y=536} " Growth="1 " GrowthB="0">
                <Link pin="I_C227_A0_P1_in" dir="in" link="Link2" />
                <Link pin="O_C227_A0_P2_out" dir="out" link="Link3" />
            </Algorithm>
            <Algorithm name="GainAlgNS145X5" friendlyname="Gain (no-slew) " cell="VibinDspCoolness.Gain1_5 " location="{X=732, Y=1129} " Growth="1 " GrowthB="0">
                <Link pin="I_C306_A0_P1_in" dir="in" link="Link23" />
                <Link pin="O_C306_A0_P2_out" dir="out" link="Link17" />
            </Algorithm>
            <Algorithm name="OneChanAccuratePeakNoPostGainS300_FullRange1" friendlyname="1-Channel Peak Compressor (Accurate) " cell="VibinDspCoolness.Compressor1 " location="{X=851, Y=526} " Growth="0 " GrowthB="0">
                <Link pin="I_C237_A0_P1_in" dir="in" link="Link3" />
                <Link pin="O_C237_A0_P2_out" dir="out" link="Link26" />
            </Algorithm>
            <Algorithm name="OneChanAccuratePeakNoPostGainS300_FullRange3" friendlyname="1-Channel Peak Compressor (Accurate) " cell="VibinDspCoolness.Compressor1_3 " location="{X=869, Y=1135} " Growth="0 " GrowthB="0">
                <Link pin="I_C255_A0_P1_in" dir="in" link="Link17" />
                <Link pin="O_C255_A0_P2_out" dir="out" link="Link28" />
            </Algorithm>
            <Algorithm name="HWGainADAU145XAlg1" friendlyname="Gain (HW slew) " cell="VibinDspCoolness.Generated Bass Volume " location="{X=1015, Y=716} " Growth="2 " GrowthB="0">
                <Link pin="I_C0_A0_P1_in" dir="in" link="Link26" />
                <Link pin="I_C0_A0_P3_in" dir="in" link="Link28" />
                <Link pin="O_C0_A0_P2_out" dir="out" link="Link27" />
                <Link pin="O_C0_A0_P4_out" dir="out" link="Link29" />
            </Algorithm>
            <Algorithm name="AdderAlg145X2" friendlyname="Addition " cell="VibinDspCoolness.Add2 " location="{X=1105, Y=475} " Growth="2 " GrowthB="0">
                <Link pin="I_C103_A0_P2_in" dir="in" link="Link12" />
                <Link pin="I_C103_A0_P3_in" dir="in" link="Link27" />
                <Link pin="O_C103_A0_P1_out" dir="out" link="Link11" />
            </Algorithm>
            <Algorithm name="AdderAlg145X1" friendlyname="Addition " cell="VibinDspCoolness.Add2_2 " location="{X=1123, Y=1084} " Growth="2 " GrowthB="0">
                <Link pin="I_C283_A0_P2_in" dir="in" link="Link18" />
                <Link pin="I_C283_A0_P3_in" dir="in" link="Link29" />
                <Link pin="O_C283_A0_P1_out" dir="out" link="Link24" />
            </Algorithm>
            <Algorithm name="GainAlgNS145X3" friendlyname="Gain (no-slew) " cell="VibinDspCoolness.Gain1_3 " location="{X=1222, Y=445} " Growth="1 " GrowthB="0">
                <Link pin="I_C266_A0_P1_in" dir="in" link="Link11" />
                <Link pin="O_C266_A0_P2_out" dir="out" link="Link41" />
            </Algorithm>
            <Algorithm name="GainAlgNS145X6" friendlyname="Gain (no-slew) " cell="VibinDspCoolness.Gain1_6 " location="{X=1240, Y=1054} " Growth="1 " GrowthB="0">
                <Link pin="I_C312_A0_P1_in" dir="in" link="Link24" />
                <Link pin="O_C312_A0_P2_out" dir="out" link="Link43" />
            </Algorithm>
            <Algorithm name="DelaySigma300Alg3" friendlyname="Growable Delay " cell="Delay_C " location="{X=606, Y=705} " Growth="1 " GrowthB="0">
                <Link pin="I_C111_A0_P1_in" dir="in" link="Link41" />
                <Link pin="O_C111_A0_P2_out" dir="out" link="Link33" />
            </Algorithm>
            <Algorithm name="DelaySigma300PMAlg2" friendlyname="Growable Delay " cell="Delay_C " location="{X=606, Y=705} " Growth="1 " GrowthB="0">
                <Link pin="I_C111_A1_P1_in" dir="in" link="Link43" />
                <Link pin="O_C111_A1_P2_out" dir="out" link="Link34" />
            </Algorithm>
            <Algorithm name="NthOrderDoubleS3005" friendlyname="N Channel - Double Precision " cell="NFilter1_5 " location="{X=750, Y=745} " Growth="2 " GrowthB="0">
                <Link pin="I_C4_A0_P1_in" dir="in" link="Link33" />
                <Link pin="I_C4_A0_P3_in" dir="in" link="Link34" />
                <Link pin="O_C4_A0_P2_out" dir="out" link="Link31" />
                <Link pin="O_C4_A0_P4_out" dir="out" link="Link35" />
            </Algorithm>
            <Algorithm name="NthOrderDoubleS3001" friendlyname="N Channel - Double Precision " cell="NFilter1 " location="{X=902, Y=742} " Growth="2 " GrowthB="0">
                <Link pin="I_C517_A0_P1_in" dir="in" link="Link31" />
                <Link pin="I_C517_A0_P3_in" dir="in" link="Link35" />
                <Link pin="O_C517_A0_P2_out" dir="out" link="Link36" />
                <Link pin="O_C517_A0_P4_out" dir="out" link="Link37" />
            </Algorithm>
            <Algorithm name="DCBlockAlgDblPrecS3003" friendlyname="DC Blocking " cell="DCB1 " location="{X=1040, Y=586.4836} " Growth="0 " GrowthB="0">
                <Link pin="I_C29_A2_P1_in" dir="in" link="Link36" />
                <Link pin="O_C29_A2_P2_out" dir="out" link="Link44" />
            </Algorithm>
            <Algorithm name="DCBlockAlgDblPrecS3004" friendlyname="DC Blocking " cell="DCB1 " location="{X=1040, Y=586.4836} " Growth="0 " GrowthB="0">
                <Link pin="I_C29_A3_P1_in" dir="in" link="Link37" />
                <Link pin="O_C29_A3_P2_out" dir="out" link="Link45" />
            </Algorithm>
            <Algorithm name="ICOutADAU145X3" friendlyname="Output " cell="Output3 " location="{X=1364, Y=598} " Growth="1 " GrowthB="0">
                <Link pin="I_C39_A0_P1_in" dir="in" link="Link44" />
            </Algorithm>
            <Algorithm name="ICOutADAU145X4" friendlyname="Output " cell="Output3_2 " location="{X=1414, Y=648} " Growth="1 " GrowthB="0">
                <Link pin="I_C41_A0_P1_in" dir="in" link="Link44" />
            </Algorithm>
            <Algorithm name="ICOutADAU145X5" friendlyname="Output " cell="Output3_3 " location="{X=1464, Y=698} " Growth="1 " GrowthB="0">
                <Link pin="I_C44_A0_P1_in" dir="in" link="Link44" />
            </Algorithm>
            <Algorithm name="ICOutADAU145X6" friendlyname="Output " cell="Output3_4 " location="{X=1367, Y=744} " Growth="1 " GrowthB="0">
                <Link pin="I_C57_A0_P1_in" dir="in" link="Link45" />
            </Algorithm>
            <Algorithm name="ICOutADAU145X7" friendlyname="Output " cell="Output3_5 " location="{X=1417, Y=794} " Growth="1 " GrowthB="0">
                <Link pin="I_C59_A0_P1_in" dir="in" link="Link45" />
            </Algorithm>
            <Algorithm name="ICOutADAU145X8" friendlyname="Output " cell="Output3_6 " location="{X=1467, Y=844} " Growth="1 " GrowthB="0">
                <Link pin="I_C88_A0_P1_in" dir="in" link="Link45" />
            </Algorithm>
        </Schematic>
    </IC>
</NetList>